ProcessOptimizer/__init__.py
ProcessOptimizer/acquisition.py
ProcessOptimizer/bokeh_plot.py
ProcessOptimizer/callbacks.py
ProcessOptimizer/plots.py
ProcessOptimizer/searchcv.py
ProcessOptimizer/XpyriMentor/__init__.py
ProcessOptimizer/XpyriMentor/xpyrimentor.py
ProcessOptimizer/XpyriMentor/suggestors/__init__.py
ProcessOptimizer/XpyriMentor/suggestors/default_suggestor.py
ProcessOptimizer/XpyriMentor/suggestors/lhs_suggestor.py
ProcessOptimizer/XpyriMentor/suggestors/po_suggestor.py
ProcessOptimizer/XpyriMentor/suggestors/random_strategizer.py
ProcessOptimizer/XpyriMentor/suggestors/sequential_strategizer.py
ProcessOptimizer/XpyriMentor/suggestors/suggestor.py
ProcessOptimizer/XpyriMentor/suggestors/suggestor_factory.py
ProcessOptimizer/learning/__init__.py
ProcessOptimizer/learning/cook_estimator.py
ProcessOptimizer/learning/forest.py
ProcessOptimizer/learning/gbrt.py
ProcessOptimizer/learning/has_gradients.py
ProcessOptimizer/learning/use_named_args.py
ProcessOptimizer/learning/gaussian_process/__init__.py
ProcessOptimizer/learning/gaussian_process/gpr.py
ProcessOptimizer/learning/gaussian_process/kernels.py
ProcessOptimizer/model_systems/__init__.py
ProcessOptimizer/model_systems/benchmarks.py
ProcessOptimizer/model_systems/branin_hoo.py
ProcessOptimizer/model_systems/color_pH.py
ProcessOptimizer/model_systems/gold_map.py
ProcessOptimizer/model_systems/gold_map_with_wells.py
ProcessOptimizer/model_systems/hart3.py
ProcessOptimizer/model_systems/hart6.py
ProcessOptimizer/model_systems/model_system.py
ProcessOptimizer/model_systems/model_system_getter.py
ProcessOptimizer/model_systems/noise_models.py
ProcessOptimizer/model_systems/peaks.py
ProcessOptimizer/model_systems/poly2.py
ProcessOptimizer/model_systems/data/color_pH_data.csv
ProcessOptimizer/optimizer/_NSGA2.py
ProcessOptimizer/optimizer/__init__.py
ProcessOptimizer/optimizer/base.py
ProcessOptimizer/optimizer/dummy.py
ProcessOptimizer/optimizer/forest.py
ProcessOptimizer/optimizer/gbrt.py
processoptimizer-1.1.1.dist-info/AUTHORS_scikit_optimize.md
processoptimizer-1.1.1.dist-info/LICENSE.md
processoptimizer-1.1.1.dist-info/METADATA
processoptimizer-1.1.1.dist-info/WHEEL
processoptimizer-1.1.1.dist-info/top_level.txt
processoptimizer-1.1.1.dist-info/RECORD
