Metadata-Version: 2.2
Name: ProcessOptimizer
Version: 1.1.1
Summary: Sequential model-based optimization toolbox (forked from scikit-optimize)
Author: Novo Nordisk, Research & Early Development
License: BSD
Project-URL: homepage, https://github.com/novonordisk-research/ProcessOptimizer
Classifier: Development Status :: 5 - Production/Stable
Classifier: Intended Audience :: Developers
Classifier: Intended Audience :: Science/Research
Classifier: License :: OSI Approved :: BSD License
Classifier: Operating System :: OS Independent
Classifier: Programming Language :: Python :: 3
Classifier: Programming Language :: Python :: 3.9
Classifier: Programming Language :: Python :: 3.10
Classifier: Programming Language :: Python :: 3.11
Classifier: Programming Language :: Python :: 3.12
Classifier: Topic :: Scientific/Engineering
Classifier: Topic :: Scientific/Engineering :: Artificial Intelligence
Classifier: Topic :: Software Development :: Libraries :: Python Modules
Requires-Python: >=3.6
License-File: LICENSE.md
License-File: AUTHORS_scikit_optimize.md
Requires-Dist: numpy
Requires-Dist: matplotlib
Requires-Dist: scipy
Requires-Dist: bokeh
Requires-Dist: scikit-learn>=0.24.2
Requires-Dist: six
Requires-Dist: deap
Requires-Dist: pyYAML
Requires-Dist: patsy
Provides-Extra: browniebee
Requires-Dist: bokeh==3.4.1; extra == "browniebee"
Requires-Dist: deap==1.4.1; extra == "browniebee"
Requires-Dist: matplotlib==3.8.4; extra == "browniebee"
Requires-Dist: numpy==1.26.4; extra == "browniebee"
Requires-Dist: pyYAML==6.0.1; extra == "browniebee"
Requires-Dist: scikit-learn==1.4.2; extra == "browniebee"
Requires-Dist: scipy==1.13.0; extra == "browniebee"
Requires-Dist: six==1.16.0; extra == "browniebee"
Requires-Dist: patsy==1.0.1; extra == "browniebee"
Provides-Extra: release
Requires-Dist: build==1.2.2.post1; extra == "release"
